LICENSE
MANIFEST.in
README.md
requirements.txt
setup.py
mytonlib/__init__.py
mytonlib/adnl.py
mytonlib/balancer.py
mytonlib/block.fixes.tlb
mytonlib/boc.py
mytonlib/mytypes.py
mytonlib/scanner.py
mytonlib/tests.py
mytonlib/tl.py
mytonlib/tlb.py
mytonlib/utils.py
mytonlib.egg-info/PKG-INFO
mytonlib.egg-info/SOURCES.txt
mytonlib.egg-info/dependency_links.txt
mytonlib.egg-info/requires.txt
mytonlib.egg-info/top_level.txt