Metadata-Version: 2.1
Name: mytonlib
Version: 0.7.4
Summary: Native library for working with TON (The Open Network)
Home-page: https://github.com/igroman787/mytonlib
Author: Igroman787
License: UNKNOWN
Platform: UNKNOWN
Requires-Python: >=3.7
License-File: LICENSE
